.DS_Store
car_speed/__init__.py
car_speed/car_speed_detection.py
tests/__init__.py
tests/car_speed_detection_test.py
car_speed_detection-1.7.0.dist-info/LICENSE.txt
car_speed_detection-1.7.0.dist-info/METADATA
car_speed_detection-1.7.0.dist-info/WHEEL
car_speed_detection-1.7.0.dist-info/top_level.txt
car_speed_detection-1.7.0.dist-info/RECORD
