Metadata-Version: 2.1
Name: car-speed-detection
Version: 1.7.0
Summary: Camera-based Car Speed Detection for Autonomous Driving
Home-page: UNKNOWN
Author: Shao-chieh Lien
Author-email: shaochiehlien@gmail.com
License: MIT
Keywords: python,car speed detection,software-based speedometer,dashboard camera,optical flow,machine learning,keras
Platform: UNKNOWN
Classifier: Development Status :: 4 - Beta
Classifier: Intended Audience :: Developers
Classifier: Programming Language :: Python :: 3
Classifier: Operating System :: MacOS :: MacOS X
Classifier: Operating System :: Microsoft :: Windows
Requires-Dist: absl-py (==0.12.0)
Requires-Dist: astunparse (==1.6.3)
Requires-Dist: cachetools (==4.2.1)
Requires-Dist: car-speed-detection (==0.7.4)
Requires-Dist: certifi (==2020.12.5)
Requires-Dist: chardet (==4.0.0)
Requires-Dist: cycler (==0.10.0)
Requires-Dist: flatbuffers (==1.12)
Requires-Dist: gast (==0.3.3)
Requires-Dist: google-auth (==1.28.1)
Requires-Dist: google-auth-oauthlib (==0.4.4)
Requires-Dist: google-pasta (==0.2.0)
Requires-Dist: grpcio (==1.32.0)
Requires-Dist: h5py (==2.10.0)
Requires-Dist: idna (==2.10)
Requires-Dist: joblib (==1.0.1)
Requires-Dist: Keras-Preprocessing (==1.1.2)
Requires-Dist: kiwisolver (==1.3.1)
Requires-Dist: Markdown (==3.3.4)
Requires-Dist: matplotlib (==3.3.4)
Requires-Dist: numpy (==1.19.4)
Requires-Dist: oauthlib (==3.1.0)
Requires-Dist: opencv-python (==4.5.1.48)
Requires-Dist: opt-einsum (==3.3.0)
Requires-Dist: pandas (==1.2.1)
Requires-Dist: Pillow (==8.2.0)
Requires-Dist: protobuf (==3.15.8)
Requires-Dist: pyasn1 (==0.4.8)
Requires-Dist: pyasn1-modules (==0.2.8)
Requires-Dist: pyparsing (==2.4.7)
Requires-Dist: python-dateutil (==2.8.1)
Requires-Dist: pytz (==2021.1)
Requires-Dist: requests (==2.25.1)
Requires-Dist: requests-oauthlib (==1.3.0)
Requires-Dist: rsa (==4.7.2)
Requires-Dist: scikit-learn (==0.24.1)
Requires-Dist: scipy (==1.6.2)
Requires-Dist: six (==1.15.0)
Requires-Dist: sklearn (==0.0)
Requires-Dist: tensorboard (==2.4.1)
Requires-Dist: tensorboard-plugin-wit (==1.8.0)
Requires-Dist: tensorflow (==2.4.1)
Requires-Dist: tensorflow-estimator (==2.4.0)
Requires-Dist: termcolor (==1.1.0)
Requires-Dist: threadpoolctl (==2.1.0)
Requires-Dist: typing-extensions (==3.7.4.3)
Requires-Dist: urllib3 (==1.26.4)
Requires-Dist: Werkzeug (==1.0.1)
Requires-Dist: wrapt (==1.12.1)
